sbpkg/__init__.py
sbpkg/chars.py
sbpkg/cli_help.py
sbpkg/config.py
sbpkg/main.py
sbpkg/metadata.py
sbpkg/pb_config.py
sbpkg/sbo_generate.py
sbpkg/support.py
sbpkg/utils.py
sbpkg-1.1.4.dist-info/entry_points.txt
sbpkg-1.1.4.dist-info/licenses/LICENSE.txt
sbpkg-1.1.4.dist-info/WHEEL
sbpkg-1.1.4.dist-info/METADATA
sbpkg-1.1.4.dist-info/RECORD
