Metadata-Version: 2.4
Name: sbpkg
Version: 1.1.4
Summary: Simple, fast and full-featured SBo package manager
Keywords: slackware,linux,package,manager,tool
Author-email: Dimitris Zlatanidis <dslackw@gmail.com>
Maintainer-email: Dimitris Zlatanidis <dslackw@gmail.com>
Requires-Python: >=3.9
Classifier: License :: OSI Approved :: GNU General Public License v3 (GPLv3)
Classifier: Natural Language :: English
Classifier: Environment :: Console
Classifier: Operating System :: POSIX
Classifier: Operating System :: POSIX :: Linux
Classifier: Programming Language :: Python
Classifier: Programming Language :: Python :: 3
Classifier: Programming Language :: Unix Shell
Classifier: Topic :: Utilities
Classifier: Topic :: Software Development :: Build Tools
Classifier: Topic :: System :: Archiving :: Packaging
Classifier: Topic :: System :: Software Distribution
Classifier: Topic :: System :: Installation/Setup
Classifier: Topic :: System :: Systems Administration
Classifier: Topic :: System :: Software Distribution
Classifier: Development Status :: 5 - Production/Stable
License-File: LICENSE.txt
Project-URL: Changelog, https://gitlab.com/dslackw/sbpkg/-/blob/main/ChangeLog.md
Project-URL: Documentation, https://gitlab.com/dslackw/sbpkg
Project-URL: Homepage, https://gitlab.com/dslackw/sbpkg
Project-URL: Repository, https://gitlab.com/dslackw/sbpkg.git
